LICENSE.txt
MANIFEST.in
README.md
setup.cfg
setup.py
handytools/__init__.py
handytools/mail.py
handytools/op.py
handytools/thread.py
handytools.egg-info/PKG-INFO
handytools.egg-info/SOURCES.txt
handytools.egg-info/dependency_links.txt
handytools.egg-info/requires.txt
handytools.egg-info/top_level.txt