Metadata-Version: 2.1
Name: handytools
Version: 0.0.5.3
Summary: So far, contains string and file processing tools.
Home-page: https://github.com/TITC/handytools
Download-URL: https://github.com/TITC/handytools/archive/refs/tags/0.0.5.3.tar.gz
Author: Yuhang Tao
Author-email: yuhang.tao.email@gmail.com
License: MIT
Keywords: nlp,file,regex
Platform: UNKNOWN
Classifier: Development Status :: 3 - Alpha
Classifier: Intended Audience :: Developers
Classifier: Topic :: Software Development :: Build Tools
Classifier: License :: OSI Approved :: MIT License
Classifier: Programming Language :: Python :: 3.8
License-File: LICENSE.txt
